schemaql/__init__.py
schemaql/aggregator.py
schemaql/collector.py
schemaql/collectors.py
schemaql/generator.py
schemaql/jinja.py
schemaql/main.py
schemaql/metrics.py
schemaql/project.py
schemaql/tester.py
schemaql/connectors/__init__.py
schemaql/connectors/base_connector.py
schemaql/connectors/bigquery.py
schemaql/connectors/snowflake.py
schemaql/helpers/__init__.py
schemaql/helpers/fileio.py
schemaql/helpers/logger.py
schemaql/include/templates/macros/connector_macro.sql
schemaql/include/templates/macros/current_timestamp.sql
schemaql/include/templates/macros/datatypes.sql
schemaql/include/templates/macros/dateadd.sql
schemaql/include/templates/macros/hash.sql
schemaql/include/templates/macros/safe_cast.sql
schemaql/include/templates/metrics/count_distinct.sql
schemaql/include/templates/metrics/mean.sql
schemaql/include/templates/metrics/row_count.sql
schemaql/include/templates/metrics/sum.sql
schemaql/include/templates/tests/data/accepted_values.sql
schemaql/include/templates/tests/data/at_least_one.sql
schemaql/include/templates/tests/data/expression_is_true.sql
schemaql/include/templates/tests/data/is_between.sql
schemaql/include/templates/tests/data/not_accepted_values.sql
schemaql/include/templates/tests/data/not_constant.sql
schemaql/include/templates/tests/data/not_empty_string.sql
schemaql/include/templates/tests/data/recency.sql
schemaql/include/templates/tests/data/unique_rows.sql
schemaql/include/templates/tests/data/value_length.sql
schemaql/include/templates/tests/schema/not_null.sql
schemaql/include/templates/tests/schema/relationships.sql
schemaql/include/templates/tests/schema/unique.sql
schemaql/include/templates/yaml/schema.yml
schemaql-0.0.4.data/scripts/schemaql
schemaql-0.0.4.dist-info/LICENSE
schemaql-0.0.4.dist-info/METADATA
schemaql-0.0.4.dist-info/WHEEL
schemaql-0.0.4.dist-info/top_level.txt
schemaql-0.0.4.dist-info/RECORD
