Metadata-Version: 2.1
Name: schemaql
Version: 0.0.4
Summary: A testing and auditing tool inspired by dbt, for those not using dbt.
Home-page: https://schemaql.com
Author: Calogica, LLC
Author-email: info@calogica.com
License: UNKNOWN
Platform: UNKNOWN
Classifier: Development Status :: 3 - Alpha
Classifier: License :: OSI Approved :: GNU General Public License v3 or later (GPLv3+)
Classifier: Operating System :: MacOS :: MacOS X
Classifier: Operating System :: POSIX :: Linux
Classifier: Programming Language :: Python :: 3.6
Classifier: Programming Language :: Python :: 3.7
Classifier: Programming Language :: Python :: 3.8
Requires-Python: >=3.6
Requires-Dist: cffi (==1.13.0)
Requires-Dist: Jinja2 (>=2.10)
Requires-Dist: PyYAML (>=5.1)
Requires-Dist: plac (>=1.0.0)
Requires-Dist: pybigquery (>=0.4.11)
Requires-Dist: colorama (==0.3.9)
Requires-Dist: snowflake-connector-python (==2.0.3)
Requires-Dist: snowflake-sqlalchemy (>=1.1.14)
Requires-Dist: SQLAlchemy (>=1.3.7)
Requires-Dist: sqlalchemy-redshift (>=0.7.5)
Requires-Dist: psycopg2 (<2.8,>=2.7.5)
